anubis/API.py
anubis/__init__.py
anubis/cli.py
anubis/commands/__init__.py
anubis/commands/base.py
anubis/commands/target.py
anubis/scanners/__init__.py
anubis/scanners/anubis_db.py
anubis/scanners/censys.py
anubis/scanners/crt.py
anubis/scanners/dnsdumpster.py
anubis/scanners/dnssec.py
anubis/scanners/hackertarget.py
anubis/scanners/hudson_rock.py
anubis/scanners/netcraft.py
anubis/scanners/nmap.py
anubis/scanners/pkey.py
anubis/scanners/recursive.py
anubis/scanners/shodan.py
anubis/scanners/spyse.py
anubis/scanners/ssl.py
anubis/scanners/zonetransfer.py
anubis/utils/__init__.py
anubis/utils/color_print.py
anubis/utils/search_worker.py
anubis/utils/signal_handler.py
anubis_netsec-1.3.1.dist-info/LICENSE
anubis_netsec-1.3.1.dist-info/METADATA
anubis_netsec-1.3.1.dist-info/WHEEL
anubis_netsec-1.3.1.dist-info/entry_points.txt
anubis_netsec-1.3.1.dist-info/top_level.txt
anubis_netsec-1.3.1.dist-info/RECORD
