Metadata-Version: 2.2
Name: anubis-netsec
Version: 1.3.1
Summary: Modern and efficient subdomain enumeration and information gathering
Home-page: https://github.com/jonluca/anubis
Author: JonLuca DeCaro
Author-email: jonluca.decaro@gmail.com
License: MIT
Keywords: cli
Classifier: Intended Audience :: Developers
Classifier: Development Status :: 3 - Alpha
Classifier: Topic :: Utilities
Classifier: License :: Public Domain
Classifier: Natural Language :: English
Classifier: Operating System :: OS Independent
Classifier: Programming Language :: Python :: 3.4
Classifier: Programming Language :: Python :: 3.5
Classifier: Programming Language :: Python :: 3.6
Requires-Python: >=3
License-File: LICENSE
Requires-Dist: setuptools
Requires-Dist: python_nmap==0.7.1
Requires-Dist: shodan>=1.31.0
Requires-Dist: docopt==0.6.2
Requires-Dist: requests>=2.32.3
Requires-Dist: censys==2.2.16
Requires-Dist: dnspython>=2.7.0
Provides-Extra: test
Requires-Dist: coverage; extra == "test"
Requires-Dist: pytest; extra == "test"
Requires-Dist: pytest-cov; extra == "test"
Dynamic: author
Dynamic: author-email
Dynamic: classifier
Dynamic: description
Dynamic: description-content-type
Dynamic: home-page
Dynamic: keywords
Dynamic: license
Dynamic: provides-extra
Dynamic: requires-dist
Dynamic: requires-python
Dynamic: summary
